<?xml version="1.0" encoding="UTF-8"?>
<flow id="09b7dfea-13a4-45df-aaa0-5596aa48c825">
  <descriptionCdata><![CDATA[09b7dfea-13a4-45df-aaa0-5596aa48c825.1d5e11c4-e652-490c-bdce-914a349f05eb.description=<pre>\nSubtracts two numbers\n\nInputs\:\nvalue1 - The first value.\nvalue2 - The second value.\n\nReturns\:\nThe difference of the two numbers.\n\nResponses\:\nsuccess - The operation completed successfully.\nfailure - Something went wrong.\n</pre>
09b7dfea-13a4-45df-aaa0-5596aa48c825.3ab9ec7d-aabd-40be-8c1b-a3a73616a929.prompt=Enter a value\:
09b7dfea-13a4-45df-aaa0-5596aa48c825.4758c5bf-c643-4484-9c72-b4d0aee56ff7.prompt=Enter value\:
]]></descriptionCdata>
  <annotation></annotation>
  <name>subtractionflow</name>
  <categories/>
  <inputs>
    <userInputBinding id="4758c5bf-c643-4484-9c72-b4d0aee56ff7">
      <annotation></annotation>
      <assignFromContext>false</assignFromContext>
      <assignToContext>false</assignToContext>
      <inputType>STRING</inputType>
      <isList>false</isList>
      <required>false</required>
      <isPersisted>true</isPersisted>
      <inputSymbol>input1</inputSymbol>
      <listDelimiter>,</listDelimiter>
      <record>false</record>
      <prompt>09b7dfea-13a4-45df-aaa0-5596aa48c825.4758c5bf-c643-4484-9c72-b4d0aee56ff7.prompt</prompt>
      <isMultiSelect>false</isMultiSelect>
      <sourceDelimiter>|</sourceDelimiter>
    </userInputBinding>
    <userInputBinding id="3ab9ec7d-aabd-40be-8c1b-a3a73616a929">
      <annotation></annotation>
      <assignFromContext>false</assignFromContext>
      <assignToContext>false</assignToContext>
      <inputType>STRING</inputType>
      <isList>false</isList>
      <required>false</required>
      <isPersisted>true</isPersisted>
      <inputSymbol>input2</inputSymbol>
      <listDelimiter>,</listDelimiter>
      <record>false</record>
      <prompt>09b7dfea-13a4-45df-aaa0-5596aa48c825.3ab9ec7d-aabd-40be-8c1b-a3a73616a929.prompt</prompt>
      <isMultiSelect>false</isMultiSelect>
      <sourceDelimiter>|</sourceDelimiter>
    </userInputBinding>
  </inputs>
  <possibleResponses>
    <opResponse id="5380face-ab52-4c5d-a2f4-1d30491d3c1a">
      <annotation></annotation>
      <name>success</name>
      <isDefault>true</isDefault>
      <onFailure>false</onFailure>
      <type>RESOLVED</type>
      <matchRules/>
    </opResponse>
    <opResponse id="8c4081e4-e5b0-44f0-b187-b60c40332212">
      <annotation></annotation>
      <name>failure</name>
      <isDefault>false</isDefault>
      <onFailure>true</onFailure>
      <type>ERROR</type>
      <matchRules/>
    </opResponse>
  </possibleResponses>
  <availableResultExpressions/>
  <resultExpression id="c1c9b43b-35dc-4992-98dd-0a73f1e8589f">
    <annotation></annotation>
    <name>FailureMessage</name>
    <fieldName>FailureMessage</fieldName>
    <sourceType>RAWRESULT</sourceType>
    <filters/>
  </resultExpression>
  <iconSpec id="6cc699a7-8063-4694-8d5f-d25a1052662e">
    <baseIcon>flow.png</baseIcon>
    <basePath>System</basePath>
    <readOnly>false</readOnly>
    <layers/>
  </iconSpec>
  <callouts/>
  <checkPointFlow>true</checkPointFlow>
  <compatibleRuntimeContext>false</compatibleRuntimeContext>
  <historyCheckPointFlow>true</historyCheckPointFlow>
  <steps>
    <step id="1d5e11c4-e652-490c-bdce-914a349f05eb">
      <annotation>09b7dfea-13a4-45df-aaa0-5596aa48c825.1d5e11c4-e652-490c-bdce-914a349f05eb.description</annotation>
      <name>Subtraction</name>
      <bounds>
        <x>190.0</x>
        <y>121.0</y>
      </bounds>
      <layer>-1</layer>
      <hideInbound>false</hideInbound>
      <iconSpec id="d3a6e26c-279c-4fcd-b9a1-b2292ae07908">
        <baseIcon>calculator.png</baseIcon>
        <basePath>Others</basePath>
        <readOnly>false</readOnly>
        <layers/>
      </iconSpec>
      <addResultToRunContext>false</addResultToRunContext>
      <isCriticalStep>false</isCriticalStep>
      <isNonBlocking>false</isNonBlocking>
      <isParallelStep>false</isParallelStep>
      <isSingleResponse>false</isSingleResponse>
      <recordInHistory>false</recordInHistory>
      <recordRawOutput>true</recordRawOutput>
      <recordPrimaryOutput>true</recordPrimaryOutput>
      <checkPointStep>true</checkPointStep>
      <historyCheckPointStep>true</historyCheckPointStep>
      <scriptResultStep>false</scriptResultStep>
      <userPrompt></userPrompt>
      <bindings>
        <staticBinding id="48da5ddd-5f35-4df4-93eb-1525289b5e0c">
          <annotation></annotation>
          <fromContextKey>input1</fromContextKey>
          <assignFromContext>true</assignFromContext>
          <assignToContext>false</assignToContext>
          <inputType>STRING</inputType>
          <isList>false</isList>
          <required>true</required>
          <isPersisted>true</isPersisted>
          <inputSymbol>value1</inputSymbol>
          <listDelimiter>,</listDelimiter>
          <value></value>
          <record>false</record>
          <validationFormat>
            <refId>69c5e11d-2f62-488c-b02b-9c507dcb9088</refId>
            <refName>numeric</refName>
          </validationFormat>
        </staticBinding>
        <staticBinding id="a2b957e4-d6ec-4ee9-88a3-e073e25535a9">
          <annotation></annotation>
          <fromContextKey>input2</fromContextKey>
          <assignFromContext>true</assignFromContext>
          <assignToContext>false</assignToContext>
          <inputType>STRING</inputType>
          <isList>false</isList>
          <required>true</required>
          <isPersisted>true</isPersisted>
          <inputSymbol>value2</inputSymbol>
          <listDelimiter>,</listDelimiter>
          <value></value>
          <record>false</record>
          <validationFormat>
            <refId>69c5e11d-2f62-488c-b02b-9c507dcb9088</refId>
            <refName>numeric</refName>
          </validationFormat>
        </staticBinding>
        <staticBinding id="3a703fad-c400-4a4f-b999-fc02dd52caf0">
          <annotation></annotation>
          <toContextKey></toContextKey>
          <fromContextKey></fromContextKey>
          <assignFromContext>false</assignFromContext>
          <assignToContext>false</assignToContext>
          <inputType>STRING</inputType>
          <recordKey></recordKey>
          <isList>false</isList>
          <required>false</required>
          <isPersisted>true</isPersisted>
          <inputSymbol>operation</inputSymbol>
          <listDelimiter></listDelimiter>
          <value>-</value>
          <record>false</record>
        </staticBinding>
      </bindings>
      <transitions>
        <transition id="612c3490-fb83-4545-81a2-f280947b7c36">
          <annotation></annotation>
          <name>success</name>
          <command>NEXT</command>
          <linkMode>false</linkMode>
          <responseSymbol>success</responseSymbol>
          <shouldHandoff>false</shouldHandoff>
          <transitionValue>0.0</transitionValue>
          <destination>
            <refId>e6760913-2616-4639-99ab-87adc131b487</refId>
          </destination>
          <source>
            <refId>1d5e11c4-e652-490c-bdce-914a349f05eb</refId>
          </source>
          <positions>
            <point>
              <x>240.0</x>
              <y>155.0</y>
            </point>
            <point>
              <x>463.0</x>
              <y>158.0</y>
            </point>
          </positions>
          <labelPosition>
            <x>333.0</x>
            <y>0.0</y>
          </labelPosition>
        </transition>
        <transition id="5f3cd093-180d-417b-ab52-3b88366b1b88">
          <annotation></annotation>
          <name>failure</name>
          <command>NEXT</command>
          <linkMode>false</linkMode>
          <responseSymbol>failure</responseSymbol>
          <shouldHandoff>false</shouldHandoff>
          <transitionValue>0.0</transitionValue>
          <destination>
            <refId>ff60ad6e-0ac3-47ec-ba89-4388d33df09c</refId>
          </destination>
          <source>
            <refId>1d5e11c4-e652-490c-bdce-914a349f05eb</refId>
          </source>
          <positions>
            <point>
              <x>240.0</x>
              <y>155.0</y>
            </point>
            <point>
              <x>256.0</x>
              <y>338.0</y>
            </point>
          </positions>
          <labelPosition>
            <x>333.0</x>
            <y>0.0</y>
          </labelPosition>
        </transition>
      </transitions>
      <properties/>
      <opRef>
        <refId>2d56d09b-9ac2-4f43-bfc9-2179ded42c64</refId>
      </opRef>
      <assignments/>
      <throttleSize>0</throttleSize>
    </step>
    <returnStep id="e6760913-2616-4639-99ab-87adc131b487">
      <annotation></annotation>
      <name>Resolved : success</name>
      <bounds>
        <x>413.0</x>
        <y>124.0</y>
      </bounds>
      <layer>-1</layer>
      <hideInbound>false</hideInbound>
      <iconSpec id="d2e244f6-28e7-468f-9c65-c99f93e27a62">
        <baseIcon>return_success.png</baseIcon>
        <basePath>System</basePath>
        <readOnly>true</readOnly>
        <layers/>
      </iconSpec>
      <addResultToRunContext>false</addResultToRunContext>
      <isCriticalStep>false</isCriticalStep>
      <isNonBlocking>false</isNonBlocking>
      <isParallelStep>false</isParallelStep>
      <isSingleResponse>false</isSingleResponse>
      <recordInHistory>false</recordInHistory>
      <recordRawOutput>true</recordRawOutput>
      <recordPrimaryOutput>true</recordPrimaryOutput>
      <checkPointStep>true</checkPointStep>
      <historyCheckPointStep>true</historyCheckPointStep>
      <scriptResultStep>false</scriptResultStep>
      <userPrompt></userPrompt>
      <bindings/>
      <transitions>
        <transition id="61189183-72de-44ec-9ec2-6137d9ddc8f0">
          <annotation></annotation>
          <name>return</name>
          <command>NEXT</command>
          <linkMode>false</linkMode>
          <responseSymbol>success</responseSymbol>
          <shouldHandoff>false</shouldHandoff>
          <transitionValue>0.0</transitionValue>
          <destination>
            <refId>e6760913-2616-4639-99ab-87adc131b487</refId>
          </destination>
          <source>
            <refId>e6760913-2616-4639-99ab-87adc131b487</refId>
          </source>
          <positions/>
        </transition>
      </transitions>
      <properties/>
      <returnStepType>RESOLVED</returnStepType>
      <assignments/>
    </returnStep>
    <returnStep id="ff60ad6e-0ac3-47ec-ba89-4388d33df09c">
      <annotation></annotation>
      <name>Error : failure</name>
      <bounds>
        <x>206.0</x>
        <y>304.0</y>
      </bounds>
      <layer>-1</layer>
      <hideInbound>false</hideInbound>
      <addResultToRunContext>false</addResultToRunContext>
      <isCriticalStep>false</isCriticalStep>
      <isNonBlocking>false</isNonBlocking>
      <isParallelStep>false</isParallelStep>
      <isSingleResponse>false</isSingleResponse>
      <recordInHistory>false</recordInHistory>
      <recordRawOutput>true</recordRawOutput>
      <recordPrimaryOutput>true</recordPrimaryOutput>
      <checkPointStep>true</checkPointStep>
      <historyCheckPointStep>true</historyCheckPointStep>
      <scriptResultStep>false</scriptResultStep>
      <userPrompt></userPrompt>
      <bindings/>
      <transitions>
        <transition id="a623adc1-7456-4bef-9ef2-62e33bd79b41">
          <annotation></annotation>
          <name>return</name>
          <command>NEXT</command>
          <linkMode>false</linkMode>
          <responseSymbol>failure</responseSymbol>
          <shouldHandoff>false</shouldHandoff>
          <transitionValue>0.0</transitionValue>
          <destination>
            <refId>ff60ad6e-0ac3-47ec-ba89-4388d33df09c</refId>
          </destination>
          <source>
            <refId>ff60ad6e-0ac3-47ec-ba89-4388d33df09c</refId>
          </source>
          <positions/>
        </transition>
      </transitions>
      <properties/>
      <returnStepType>ERROR</returnStepType>
      <assignments/>
    </returnStep>
  </steps>
  <startSteps>1d5e11c4-e652-490c-bdce-914a349f05eb</startSteps>
</flow>